agentipy/__init__.py
agentipy/agent/__init__.py
agentipy/agent/evm/__init__.py
agentipy/constants/__init__.py
agentipy/helpers/__init__.py
agentipy/langchain/__init__.py
agentipy/langchain/allora/__init__.py
agentipy/langchain/allora/allora_get_all_topics.py
agentipy/langchain/allora/allora_get_inference_by_topic_id.py
agentipy/langchain/allora/allora_get_price_prediction.py
agentipy/langchain/backpack/__init__.py
agentipy/langchain/backpack/account.py
agentipy/langchain/backpack/history.py
agentipy/langchain/backpack/market.py
agentipy/langchain/backpack/orders.py
agentipy/langchain/backpack/positions.py
agentipy/langchain/backpack/system.py
agentipy/langchain/coingecko/__init__.py
agentipy/langchain/coingecko/gainers.py
agentipy/langchain/coingecko/pools.py
agentipy/langchain/coingecko/token_data.py
agentipy/langchain/coingecko/trending.py
agentipy/langchain/core/__init__.py
agentipy/langchain/core/balance.py
agentipy/langchain/core/burn_and_close.py
agentipy/langchain/core/burn_and_close_multiple.py
agentipy/langchain/core/create_image.py
agentipy/langchain/core/data.py
agentipy/langchain/core/deploy_token.py
agentipy/langchain/core/fetch_price.py
agentipy/langchain/core/get_wallet_address.py
agentipy/langchain/core/report.py
agentipy/langchain/core/stake.py
agentipy/langchain/core/tps_calculator.py
agentipy/langchain/core/trade.py
agentipy/langchain/core/transfer.py
agentipy/langchain/curve/__init__.py
agentipy/langchain/curve/calculate_pump_curve.py
agentipy/langchain/curve/pump_curve_state.py
agentipy/langchain/cybersmanager/__init__.py
agentipy/langchain/cybersmanager/create_coin.py
agentipy/langchain/debridge/__init__.py
agentipy/langchain/debridge/status.py
agentipy/langchain/debridge/transaction.py
agentipy/langchain/domain/__init__.py
agentipy/langchain/domain/all_domains.py
agentipy/langchain/domain/all_top_level_domain.py
agentipy/langchain/domain/get_all_domain.py
agentipy/langchain/domain/owned_domains.py
agentipy/langchain/drift/__init__.py
agentipy-2.1.3.post4.dist-info/LICENSE.md
agentipy-2.1.3.post4.dist-info/METADATA
agentipy-2.1.3.post4.dist-info/WHEEL
agentipy-2.1.3.post4.dist-info/top_level.txt
agentipy-2.1.3.post4.dist-info/RECORD
