Metadata-Version: 2.2
Name: agentipy
Version: 2.1.3.post4
Summary: A Python toolkit for on chain agents
Home-page: https://github.com/niceberginc/agentipy
Author: Utilify
Author-email: hello@getutilify.com
Project-URL: Bug Tracker, https://github.com/niceberginc/agentipy/issues
Project-URL: Documentation, https://github.com/niceberginc/agentipy#readme
Classifier: Programming Language :: Python :: 3
Classifier: License :: OSI Approved :: MIT License
Classifier: Operating System :: OS Independent
Requires-Python: >=3.7
License-File: LICENSE.md
Requires-Dist: requests==2.32.3
Requires-Dist: python-dotenv==1.0.1
Requires-Dist: numpy<3,>=1.26.2
Requires-Dist: base58>=2.1.1
Requires-Dist: aiohttp>=3.11.10
Requires-Dist: pillow>=11.0.0
Requires-Dist: openai>=1.58.1
Requires-Dist: solana==0.35.1
Requires-Dist: solders<0.24.0,>=0.21.0
Requires-Dist: pydantic>=2.10.4
Requires-Dist: langchain>=0.3.12
Requires-Dist: anchorpy>=0.20.1
Requires-Dist: pythclient>=0.2.0
Requires-Dist: pydantic-ai>=0.0.19
Requires-Dist: cryptography>=44.0.0
Requires-Dist: pynacl>=1.5.0
Requires-Dist: backpack-exchange-sdk>=1.0.24
Requires-Dist: web3>=7.8.0
Requires-Dist: allora-sdk>=0.2.0
Requires-Dist: mcp>=1.4.0
Requires-Dist: eth_utils>=5.3.0
Requires-Dist: web3>=7.10.0
Provides-Extra: dev
Requires-Dist: pytest==8.3.4; extra == "dev"
Requires-Dist: black==24.10.0; extra == "dev"
Requires-Dist: isort>=5.10.0; extra == "dev"
Dynamic: author
Dynamic: author-email
Dynamic: classifier
Dynamic: description
Dynamic: description-content-type
Dynamic: home-page
Dynamic: project-url
Dynamic: provides-extra
Dynamic: requires-dist
Dynamic: requires-python
Dynamic: summary
